gitrm/__init__.py
gitrm/__main__.py
gitrm/cli.py
git_rm-0.1.0.dist-info/entry_points.txt
git_rm-0.1.0.dist-info/LICENSE
git_rm-0.1.0.dist-info/METADATA
git_rm-0.1.0.dist-info/WHEEL
git_rm-0.1.0.dist-info/RECORD
